{"config":{"output_file":null,"full_docs":false,"pub_only":true,"reachable_only":true,"distro_crate":false,"signatures":false,"borrow_data":false},"version":"0.19.0","compilation":{"directory":"C:\\Users\\Max\\.cargo\\registry\\src\\github.com-1ecc6299db9ec823\\quick-error-1.2.3","program":"C:\\Users\\Max\\.rustup\\toolchains\\stable-x86_64-pc-windows-msvc\\bin\\rls.exe","arguments":["--crate-name","quick_error","C:\\Users\\Max\\.cargo\\registry\\src\\github.com-1ecc6299db9ec823\\quick-error-1.2.3\\src\\lib.rs","--json=diagnostic-rendered-ansi","--crate-type","lib","--emit=dep-info,metadata","-C","debuginfo=2","-C","metadata=9ad9ae92f45e9c7b","-C","extra-filename=-9ad9ae92f45e9c7b","--out-dir","c:\\Users\\Max\\Desktop\\Coding\\Rust\\ppgenerator\\src\\osapi\\target\\rls\\debug\\deps","-L","dependency=c:\\Users\\Max\\Desktop\\Coding\\Rust\\ppgenerator\\src\\osapi\\target\\rls\\debug\\deps","--cap-lints","allow","--error-format=json","--sysroot","C:\\Users\\Max\\.rustup/toolchains/stable-x86_64-pc-windows-msvc"],"output":"c:\\Users\\Max\\Desktop\\Coding\\Rust\\ppgenerator\\src\\osapi\\target\\rls\\debug\\deps\\libquick_error-9ad9ae92f45e9c7b.rmeta"},"prelude":{"crate_id":{"name":"quick_error","disambiguator":[11998807190237649498,15317030312422447257]},"crate_root":"C:\\Users\\Max\\.cargo\\registry\\src\\github.com-1ecc6299db9ec823\\quick-error-1.2.3\\src","external_crates":[{"file_name":"C:\\Users\\Max\\.cargo\\registry\\src\\github.com-1ecc6299db9ec823\\quick-error-1.2.3\\src\\lib.rs","num":1,"id":{"name":"std","disambiguator":[7051201540145939802,10319888607268705196]}},{"file_name":"C:\\Users\\Max\\.cargo\\registry\\src\\github.com-1ecc6299db9ec823\\quick-error-1.2.3\\src\\lib.rs","num":2,"id":{"name":"core","disambiguator":[1026454463601085204,5956519655747842370]}},{"file_name":"C:\\Users\\Max\\.cargo\\registry\\src\\github.com-1ecc6299db9ec823\\quick-error-1.2.3\\src\\lib.rs","num":3,"id":{"name":"compiler_builtins","disambiguator":[14346745938995860826,6106505168515399711]}},{"file_name":"C:\\Users\\Max\\.cargo\\registry\\src\\github.com-1ecc6299db9ec823\\quick-error-1.2.3\\src\\lib.rs","num":4,"id":{"name":"rustc_std_workspace_core","disambiguator":[13202720578349867464,1862842275659476996]}},{"file_name":"C:\\Users\\Max\\.cargo\\registry\\src\\github.com-1ecc6299db9ec823\\quick-error-1.2.3\\src\\lib.rs","num":5,"id":{"name":"alloc","disambiguator":[5561144063536234256,7715548798258694697]}},{"file_name":"C:\\Users\\Max\\.cargo\\registry\\src\\github.com-1ecc6299db9ec823\\quick-error-1.2.3\\src\\lib.rs","num":6,"id":{"name":"libc","disambiguator":[14610271732418635879,6772691447709284036]}},{"file_name":"C:\\Users\\Max\\.cargo\\registry\\src\\github.com-1ecc6299db9ec823\\quick-error-1.2.3\\src\\lib.rs","num":7,"id":{"name":"unwind","disambiguator":[4406516221557685466,15675910168565901142]}},{"file_name":"C:\\Users\\Max\\.cargo\\registry\\src\\github.com-1ecc6299db9ec823\\quick-error-1.2.3\\src\\lib.rs","num":8,"id":{"name":"cfg_if","disambiguator":[15997156870004117332,17234155162274038776]}},{"file_name":"C:\\Users\\Max\\.cargo\\registry\\src\\github.com-1ecc6299db9ec823\\quick-error-1.2.3\\src\\lib.rs","num":9,"id":{"name":"backtrace","disambiguator":[5592790853754669538,10741615159245382754]}},{"file_name":"C:\\Users\\Max\\.cargo\\registry\\src\\github.com-1ecc6299db9ec823\\quick-error-1.2.3\\src\\lib.rs","num":10,"id":{"name":"rustc_demangle","disambiguator":[8783235745414743982,17300328997249526776]}},{"file_name":"C:\\Users\\Max\\.cargo\\registry\\src\\github.com-1ecc6299db9ec823\\quick-error-1.2.3\\src\\lib.rs","num":11,"id":{"name":"hashbrown","disambiguator":[1439570206316701055,1850678272192971880]}},{"file_name":"C:\\Users\\Max\\.cargo\\registry\\src\\github.com-1ecc6299db9ec823\\quick-error-1.2.3\\src\\lib.rs","num":12,"id":{"name":"rustc_std_workspace_alloc","disambiguator":[6136169599652282497,8536962176442599555]}},{"file_name":"C:\\Users\\Max\\.cargo\\registry\\src\\github.com-1ecc6299db9ec823\\quick-error-1.2.3\\src\\lib.rs","num":13,"id":{"name":"panic_unwind","disambiguator":[1707569757905254316,14241360972436779925]}}],"span":{"file_name":"C:\\Users\\Max\\.cargo\\registry\\src\\github.com-1ecc6299db9ec823\\quick-error-1.2.3\\src\\lib.rs","byte_start":0,"byte_end":43603,"line_start":1,"line_end":1262,"column_start":1,"column_end":2}},"imports":[],"defs":[{"kind":"Mod","id":{"krate":0,"index":0},"span":{"file_name":"C:\\Users\\Max\\.cargo\\registry\\src\\github.com-1ecc6299db9ec823\\quick-error-1.2.3\\src\\lib.rs","byte_start":0,"byte_end":43603,"line_start":1,"line_end":1262,"column_start":1,"column_end":2},"name":"","qualname":"::","value":"C:\\Users\\Max\\.cargo\\registry\\src\\github.com-1ecc6299db9ec823\\quick-error-1.2.3\\src\\lib.rs","parent":null,"children":[{"krate":0,"index":10},{"krate":0,"index":11},{"krate":0,"index":12},{"krate":0,"index":24},{"krate":0,"index":30},{"krate":0,"index":13},{"krate":0,"index":18}],"decl_id":null,"docs":" A macro which makes errors easy to write","sig":null,"attributes":[{"value":"warn(missing_docs)","span":{"file_name":"C:\\Users\\Max\\.cargo\\registry\\src\\github.com-1ecc6299db9ec823\\quick-error-1.2.3\\src\\lib.rs","byte_start":0,"byte_end":22,"line_start":1,"line_end":1,"column_start":1,"column_end":23}}]},{"kind":"Struct","id":{"krate":0,"index":24},"span":{"file_name":"C:\\Users\\Max\\.cargo\\registry\\src\\github.com-1ecc6299db9ec823\\quick-error-1.2.3\\src\\lib.rs","byte_start":33380,"byte_end":33387,"line_start":973,"line_end":973,"column_start":12,"column_end":19},"name":"Context","qualname":"::Context","value":"","parent":null,"children":[],"decl_id":null,"docs":" Generic context type","sig":null,"attributes":[]},{"kind":"Trait","id":{"krate":0,"index":13},"span":{"file_name":"C:\\Users\\Max\\.cargo\\registry\\src\\github.com-1ecc6299db9ec823\\quick-error-1.2.3\\src\\lib.rs","byte_start":33473,"byte_end":33482,"line_start":976,"line_end":976,"column_start":11,"column_end":20},"name":"ResultExt","qualname":"::ResultExt","value":"ResultExt<T, E>","parent":null,"children":[{"krate":0,"index":16}],"decl_id":null,"docs":" Result extension trait adding a `context` method\n","sig":null,"attributes":[]},{"kind":"Method","id":{"krate":0,"index":16},"span":{"file_name":"C:\\Users\\Max\\.cargo\\registry\\src\\github.com-1ecc6299db9ec823\\quick-error-1.2.3\\src\\lib.rs","byte_start":33826,"byte_end":33833,"line_start":983,"line_end":983,"column_start":8,"column_end":15},"name":"context","qualname":"::ResultExt::context","value":"fn <X> (self, x: X) -> Result<T, Context<X, E>>","parent":{"krate":0,"index":13},"children":[],"decl_id":null,"docs":" The method is use to add context information to current operation","sig":null,"attributes":[]}],"impls":[{"id":0,"kind":"Direct","span":{"file_name":"C:\\Users\\Max\\.cargo\\registry\\src\\github.com-1ecc6299db9ec823\\quick-error-1.2.3\\src\\lib.rs","byte_start":33912,"byte_end":33918,"line_start":986,"line_end":986,"column_start":32,"column_end":38},"value":"","parent":null,"children":[{"krate":0,"index":21}],"docs":"","sig":null,"attributes":[]}],"refs":[],"macro_refs":[],"relations":[{"span":{"file_name":"C:\\Users\\Max\\.cargo\\registry\\src\\github.com-1ecc6299db9ec823\\quick-error-1.2.3\\src\\lib.rs","byte_start":33912,"byte_end":33918,"line_start":986,"line_end":986,"column_start":32,"column_end":38},"kind":{"Impl":{"id":0}},"from":{"krate":2,"index":29496},"to":{"krate":0,"index":13}}]}